esm_efficient-0.0.9.dist-info/licenses/LICENSE
esme/__init__.py
esme/alphabet.py
esme/attention.py
esme/cli.py
esme/data.py
esme/deepspeed.py
esme/download.py
esme/embedding.py
esme/esm.py
esme/fasta.py
esme/head.py
esme/layer.py
esme/lora.py
esme/loss.py
esme/pooling.py
esme/quantization.py
esme/rotary.py
esme/trainer.py
esme/variant.py
esm_efficient-0.0.9.dist-info/METADATA
esm_efficient-0.0.9.dist-info/WHEEL
esm_efficient-0.0.9.dist-info/entry_points.txt
esm_efficient-0.0.9.dist-info/top_level.txt
esm_efficient-0.0.9.dist-info/zip-safe
esm_efficient-0.0.9.dist-info/RECORD
