Metadata-Version: 2.4
Name: esm-efficient
Version: 0.0.9
Summary: Efficient Evolutionary Scale Modeling: Efficient and simplified implementation of protein language model for inference and training.
Home-page: https://github.com/uci-cbcl/esm-efficient
License: MIT
Keywords: LLM,PLM,protein language model
License-File: LICENSE
Requires-Dist: setuptools
Requires-Dist: tqdm
Requires-Dist: torch
Requires-Dist: einops
Requires-Dist: flash_attn>2.6.3
Requires-Dist: accelerate
Requires-Dist: pandas
Requires-Dist: numpy
Requires-Dist: polars
Requires-Dist: torchmetrics
Requires-Dist: lightning
Requires-Dist: scikit-learn
Requires-Dist: huggingface_hub
Dynamic: description
Dynamic: description-content-type
Dynamic: home-page
Dynamic: keywords
Dynamic: license
Dynamic: license-file
Dynamic: requires-dist
Dynamic: summary
